walq/__init__.py
walq/client.py
walq/context.py
walq/question.py
walq/questionnaire.py
walq/response.py
walq-0.0.1.dist-info/METADATA
walq-0.0.1.dist-info/RECORD
walq-0.0.1.dist-info/WHEEL
walq-0.0.1.dist-info/top_level.txt
