Metadata-Version: 2.1
Name: walq
Version: 0.0.1
Summary: An very simple questionnaire-based chatbot
Home-page: https://github.com/pedrosiracusa/walQ
Author: Pedro C. de Siracusa
Author-email: pedrosiracusa@gmail.com
License: UNKNOWN
Platform: UNKNOWN
Classifier: Programming Language :: Python :: 3
Classifier: License :: OSI Approved :: GNU General Public License v3 (GPLv3)
Classifier: Operating System :: OS Independent
Classifier: Development Status :: 2 - Pre-Alpha
